<?xml version="1.0" encoding="utf-8"?>
<Entity parent="template_unit_champion_infantry_pikeman">
  <Armour>
    <Hack>0</Hack>
    <Pierce>0</Pierce>
    <Crush>0</Crush>
  </Armour>
  <Attack>
    <Melee>
      <Hack>0.0</Hack>
      <Pierce>65.0</Pierce>
      <Crush>0.0</Crush>
      <MaxRange>4</MaxRange>
      <PrepareTime>0</PrepareTime>
      <RepeatTime>1500</RepeatTime>
      <Bonuses>
          <BonusCavMelee>
            <Classes>Cavalry</Classes>
            <Multiplier>3.0</Multiplier>
          </BonusCavMelee>
      </Bonuses>
      <PreferredClasses datatype="tokens">Human</PreferredClasses>
    </Melee>
  </Attack>
  <Cost>
    <Resources>
      <wood>100</wood>
    </Resources>
  </Cost>
  <Health>
    <Max>200</Max>
  </Health>
  <Identity>
    <Civ>USA</Civ>
    <Lang>greek</Lang>
    <GenericName>Union Bayonet Infantry</GenericName>
    <SpecificName>Union Bayonet Infantry</SpecificName>
    <Icon>units/sele_champion_pikeman.png</Icon>
  </Identity>
  <UnitMotion>
    <WalkSpeed op="mul">1.6</WalkSpeed>
    <Run>
      <Speed op="mul">1.6</Speed>
    </Run>
  </UnitMotion>
  <VisualActor>
    <Actor>units/global/union_infantry_private.xml</Actor>
  </VisualActor>
</Entity>
